setup.py
qwertysunnyday/__init__.py
qwertysunnyday/sunnyday.py
qwertysunnyday.egg-info/PKG-INFO
qwertysunnyday.egg-info/SOURCES.txt
qwertysunnyday.egg-info/dependency_links.txt
qwertysunnyday.egg-info/requires.txt
qwertysunnyday.egg-info/top_level.txt